{
  "tripData": {
    "题目": "丹麦+瑞典+挪威+芬兰豪华行程（12天）",

    "概要": "丹麦+瑞典+挪威+芬兰豪华行程（12天）"
  },
  "daysData": [
    {
      "天数": "第一天",
      "城市": "北京-哥本哈根",
      "日期": "9月19日",
      "早餐": "/",
      "午餐": "/",
      "晚餐": "/",
      "交通": "搭乘国际航班前往丹麦首都哥本哈根。",
      "住宿": "入住位于市中心的五星商务酒店 RADISSON COLLECTION，也是世界上第一家设计酒店，很多名人政要曾下榻。",
      "活动": ["-- 抵达后接机，入住酒店。"]
    },
    {
      "天数": "第二天",
      "城市": "哥本哈根",
      "日期": "9月20日",
      "早餐": "/",
      "午餐": "/",
      "晚餐": "/",
      "交通": "/",
      "住宿": "/",
      "活动": [
        "-- 市容观光——美人鱼，皇宫外景，市政厅广场，大理石教堂。",
        "-- 前往 STROGET 步行街购物，这里大牌云集，商场林立，是北欧购物的天堂。"
      ]
    },
    {
      "天数": "第三天",
      "城市": "哥本哈根-欧登塞（安徒生故乡）",
      "日期": "9月21日",
      "早餐": "/",
      "午餐": "/",
      "晚餐": "/",
      "交通": "乘车前往2小时外的菲英岛。",
      "住宿": "/",
      "活动": [
        "-- 游览欧登塞的安徒生博物馆、安徒生故居、菲英村、伊埃斯科水上城堡。"
      ]
    },
    {
      "天数": "第四天",
      "城市": "欧登塞-奥胡斯",
      "日期": "9月22日",
      "早餐": "/",
      "午餐": "/",
      "晚餐": "/",
      "交通": "乘车抵达丹麦最具魅力的城市——奥胡斯。",
      "住宿": "/",
      "活动": [
        "-- 游览老城区露天博物馆、AROS 彩虹现代艺术博物馆、冰山现代住宅区。"
      ]
    },
    {
      "天数": "第五天",
      "城市": "奥胡斯-腓特烈港-哥德堡",
      "日期": "9月23日",
      "早餐": "/",
      "午餐": "/",
      "晚餐": "/",
      "交通": "乘车抵达腓特烈港，搭乘豪华渡轮，约3小时，乘船抵达瑞典第二大城市哥德堡。",
      "住宿": "入住当地最好水疗酒店。",
      "活动": [
        "-- 参观 VOLVO 汽车博物馆和展示厅。",
        "-- 这里也是瑞典美食的天堂，建议在“鱼教堂”大快朵颐。"
      ]
    },
    {
      "天数": "第六天",
      "城市": "哥德堡-（90公里）-斯莫根-菲耶巴卡-格列波斯塔德",
      "日期": "9月24日",
      "早餐": "/",
      "午餐": "/",
      "晚餐": "/",
      "交通": "上午乘车从哥德堡出发，抵达斯莫根。",
      "住宿": "/",
      "活动": [
        "-- 斯莫根，此行的一个高光亮点！",
        "-- 每一个到斯莫根的客人，都会觉得世界上有这种地方，是当地人的福气；而他们为自己能分享世界上的这一处美景而欣喜。",
        "-- 斯莫根是一个能让人入画的地方，沿着一公里长的木质栈道，沿途无数餐厅、私人游艇码头、纪念品商铺，每一栋房子都像是上帝精心调色画出来的。",
        "-- 这里会进入“三重醉”状态：醉氧、醉景、醉海鲜（这里可是瑞典最重要的北大西洋海产拍卖市场所在地哦）。",
        "-- 离开斯莫根，沿海岸线继续往北，不远就是另一处珍珠般的小镇——菲耶巴卡。",
        "-- 这里不仅是西瑞典有名的渔村（以螃蟹、对虾、龙虾捕捞闻名），也是瑞典国宝级影星英格丽·褒曼晚年居住的地方。1982年她去世后，大部分骨灰遵照她的遗愿，被洒在菲耶巴卡群岛的大海里。",
        "-- 这里还是瑞典著名犯罪小说家卡米拉·拉克伯格的所有犯罪小说的发生地。不过不要担心，一切在这里的旅行，都是以美好结束。"
      ]
    },
    {
      "天数": "第七天",
      "城市": "格列伯斯塔德-（100公里）-奥斯陆",
      "日期": "9月25日",
      "早餐": "/",
      "午餐": "/",
      "晚餐": "/",
      "交通": "乘车前往奥斯陆。",
      "住宿": "/",
      "活动": [
        "-- 格列伯斯塔德，这个地方的中文名字拗口，但一提到 GREBBESTAD，瑞典人大多会食指大动，馋虫上脑。",
        "-- 瑞典90%以上的生蚝，正是产于这里2-10米深的近海内。",
        "-- 并且，这里的生蚝，相对于很多人吃过的法国生蚝，以及其他一些热带地区的生蚝，有很大不同：形状扁平，其貌不扬，但吃到嘴里，有一种欲仙欲死的鲜味。",
        "-- 要知道，这里的海水冰冷，营养丰富，是北大西洋一处大自然的馈赠，所以才有可能是世界上最好吃的生蚝！",
        "-- 客人将在古老的木船上，体验捕捞生蚝的乐趣，而更大的乐趣，莫过于亲手学习用小刀打开生蚝的技巧。",
        "-- 一旦学会，您将发现入口的生蚝更加甜美，此行的高潮，又一次来临。",
        "-- 傍晚抵达挪威首都奥斯陆。"
      ]
    },
    {
      "天数": "第八天",
      "城市": "奥斯陆",
      "日期": "9月26日",
      "早餐": "/",
      "午餐": "/",
      "晚餐": "/",
      "交通": "/",
      "住宿": "/",
      "活动": [
        "-- 奥斯陆全天观光：皇宫、市政厅（诺贝尔和平奖颁发地）、和平宫、维格兰雕塑公园、跳雪台、阿克胡斯城堡、海盗船博物馆。",
        "-- 卡尔约翰大街购物。"
      ]
    },
    {
      "天数": "第九天",
      "城市": "奥斯陆-卡尔斯塔德-斯德哥尔摩",
      "日期": "9月27日",
      "早餐": "/",
      "午餐": "/",
      "晚餐": "/",
      "交通": "乘车约3个半小时，抵达瑞典中部城市卡尔斯塔德。",
      "住宿": "/",
      "活动": ["-- 午餐后，继续乘车3小时，抵达瑞典首都斯德哥尔摩。"]
    },
    {
      "天数": "第十天",
      "城市": "斯德哥尔摩-赫尔辛基",
      "日期": "9月28日",
      "早餐": "/",
      "午餐": "/",
      "晚餐": "船上享用海鲜大餐",
      "交通": "傍晚抵达码头，搭乘豪华游船，前往芬兰首都赫尔辛基。",
      "住宿": "游轮上",
      "活动": [
        "-- 上午市容游览：举办诺贝尔颁奖晚宴的市政厅、瓦萨沉船博物馆。",
        "-- 游览瑞典国王的居住地皇后岛和后花园，打卡网红景点——被誉为世界上最长的艺术长廊的斯德哥尔摩地铁。"
      ]
    },
    {
      "天数": "第十一天",
      "城市": "赫尔辛基",
      "日期": "9月29日",
      "早餐": "/",
      "午餐": "/",
      "晚餐": "/",
      "交通": "/",
      "住宿": "/",
      "活动": [
        "-- 上午抵达赫尔辛基，游览西贝柳斯公园和纪念碑，世界上唯一的岩石教堂，世界遗产芬兰堡（乘船前往），郊外的努克西奥森林公园，体验千湖之国风貌。",
        "-- 尝试芬兰最正宗的桑拿。"
      ]
    },
    {
      "天数": "第十二天",
      "城市": "赫尔辛基-北京",
      "日期": "9月30日",
      "早餐": "/",
      "午餐": "/",
      "晚餐": "/",
      "交通": "下午搭乘飞机返回北京。",
      "住宿": "/",
      "活动": ["-- 上午购物。"]
    },
    {
      "天数": "第十三天",
      "城市": "抵达北京",
      "日期": "0月1日",
      "早餐": "/",
      "午餐": "/",
      "晚餐": "/",
      "交通": "/",
      "住宿": "/",
      "活动": ["-- 抵达北京。"]
    }
  ]
}
